goat_calc/__init__.py
goat_calc/main.py
goat_calc-0.1.1.dist-info/METADATA
goat_calc-0.1.1.dist-info/WHEEL
goat_calc-0.1.1.dist-info/entry_points.txt
goat_calc-0.1.1.dist-info/RECORD
